{
  "generatedAt": "2026-06-08T06:46:27.658Z",
  "windowEnd": "2026-06-08T18:46:27.658Z",
  "referralCode": "26BC4B90CB",
  "referralLink": "https://worldcup26.world/login?ref=26BC4B90CB",
  "summary": {
    "overdueMinutes": 60,
    "overdueCount": 49,
    "dueNowCount": 1,
    "dueCount": 50,
    "upcomingCount": 12,
    "readyOutboxCount": 31,
    "loggedProofCount": 49,
    "proofedActiveCount": 6,
    "proofedDueCount": 6,
    "unloggedDueCount": 50,
    "workerCount": 4
  },
  "owners": [
    {
      "owner": "Dexter",
      "lane": "Football hooks and short feed posts",
      "overdueCount": 12,
      "dueNowCount": 1,
      "dueCount": 13,
      "upcomingCount": 3,
      "readyCount": 8,
      "next": {
        "scheduledAt": "2026-06-06T05:00:00.000Z",
        "scheduledLabel": "2026-06-06 08:00 +0300",
        "owner": "Dexter",
        "channel": "Football groups",
        "mode": "approval first",
        "action": "Ask approved group admin for permission; post group variant only if allowed",
        "asset": "campaign/first-wave-posts.md",
        "trackedLink": "https://worldcup26.world/login?ref=26BC4B90CB&utm_source=football-groups&utm_medium=approval-first&utm_campaign=worldcup26_referral_72h&utm_content=dexter_h4",
        "status": "queued"
      },
      "overdue": [
        {
          "scheduledAt": "2026-06-06T05:00:00.000Z",
          "scheduledLabel": "2026-06-06 08:00 +0300",
          "owner": "Dexter",
          "channel": "Football groups",
          "mode": "approval first",
          "action": "Ask approved group admin for permission; post group variant only if allowed",
          "asset": "campaign/first-wave-posts.md",
          "trackedLink": "https://worldcup26.world/login?ref=26BC4B90CB&utm_source=football-groups&utm_medium=approval-first&utm_campaign=worldcup26_referral_72h&utm_content=dexter_h4",
          "status": "queued"
        },
        {
          "scheduledAt": "2026-06-06T10:00:00.000Z",
          "scheduledLabel": "2026-06-06 13:00 +0300",
          "owner": "Dexter",
          "channel": "Facebook profile/page",
          "mode": "manual post",
          "action": "Publish simple rules feed post for friends and football contacts",
          "asset": "media/worldcup26-referral-square.jpg",
          "trackedLink": "https://worldcup26.world/login?ref=26BC4B90CB&utm_source=facebook-profile-page&utm_medium=manual-post&utm_campaign=worldcup26_referral_72h&utm_content=dexter_h9",
          "status": "queued"
        },
        {
          "scheduledAt": "2026-06-06T18:00:00.000Z",
          "scheduledLabel": "2026-06-06 21:00 +0300",
          "owner": "Dexter",
          "channel": "Creator outreach",
          "mode": "manual outreach",
          "action": "Send partner DM to football micro-creators",
          "asset": "campaign/first-wave-posts.md",
          "trackedLink": "https://worldcup26.world/login?ref=26BC4B90CB&utm_source=creator-outreach&utm_medium=manual-outreach&utm_campaign=worldcup26_referral_72h&utm_content=dexter_h17",
          "status": "queued"
        },
        {
          "scheduledAt": "2026-06-06T22:00:00.000Z",
          "scheduledLabel": "2026-06-07 01:00 +0300",
          "owner": "Dexter",
          "channel": "X / short feed",
          "mode": "manual post",
          "action": "Post one-month free-preview then paid-leaderboard hook",
          "asset": "media/worldcup26-referral-16x9.jpg",
          "trackedLink": "https://worldcup26.world/login?ref=26BC4B90CB&utm_source=x-short-feed&utm_medium=manual-post&utm_campaign=worldcup26_referral_72h&utm_content=dexter_h21",
          "status": "queued"
        },
        {
          "scheduledAt": "2026-06-07T01:00:00.000Z",
          "scheduledLabel": "2026-06-07 04:00 +0300",
          "owner": "Dexter",
          "channel": "Feed post",
          "mode": "manual post",
          "action": "Social proof post: ask what 3 teams friends picked",
          "asset": "media/worldcup26-referral-16x9.jpg",
          "trackedLink": "https://worldcup26.world/login?ref=26BC4B90CB&utm_source=feed-post&utm_medium=manual-post&utm_campaign=worldcup26_referral_72h&utm_content=dexter_h24",
          "status": "queued"
        },
        {
          "scheduledAt": "2026-06-07T05:00:00.000Z",
          "scheduledLabel": "2026-06-07 08:00 +0300",
          "owner": "Dexter",
          "channel": "Football groups",
          "mode": "approval first",
          "action": "Ask group admin for approved reminder slot",
          "asset": "campaign/first-wave-posts.md",
          "trackedLink": "https://worldcup26.world/login?ref=26BC4B90CB&utm_source=football-groups&utm_medium=approval-first&utm_campaign=worldcup26_referral_72h&utm_content=dexter_h28",
          "status": "queued"
        }
      ],
      "dueNow": [
        {
          "scheduledAt": "2026-06-08T06:00:00.000Z",
          "scheduledLabel": "2026-06-08 09:00 +0300",
          "owner": "Dexter",
          "channel": "Football groups",
          "mode": "approval first",
          "action": "Second approved admin post/reminder where allowed",
          "asset": "campaign/first-wave-posts.md",
          "trackedLink": "https://worldcup26.world/login?ref=26BC4B90CB&utm_source=football-groups&utm_medium=approval-first&utm_campaign=worldcup26_referral_72h&utm_content=dexter_h53",
          "status": "queued"
        }
      ],
      "upcoming": [
        {
          "scheduledAt": "2026-06-08T10:00:00.000Z",
          "scheduledLabel": "2026-06-08 13:00 +0300",
          "owner": "Dexter",
          "channel": "X / short feed",
          "mode": "manual post",
          "action": "Post late-night simple rules recap",
          "asset": "media/worldcup26-referral-square.jpg",
          "trackedLink": "https://worldcup26.world/login?ref=26BC4B90CB&utm_source=x-short-feed&utm_medium=manual-post&utm_campaign=worldcup26_referral_72h&utm_content=dexter_h57",
          "status": "queued"
        },
        {
          "scheduledAt": "2026-06-08T13:00:00.000Z",
          "scheduledLabel": "2026-06-08 16:00 +0300",
          "owner": "Dexter",
          "channel": "Football groups",
          "mode": "approval first",
          "action": "Approved reminder only where prior permission exists",
          "asset": "campaign/first-wave-posts.md",
          "trackedLink": "https://worldcup26.world/login?ref=26BC4B90CB&utm_source=football-groups&utm_medium=approval-first&utm_campaign=worldcup26_referral_72h&utm_content=dexter_h60",
          "status": "queued"
        },
        {
          "scheduledAt": "2026-06-08T18:00:00.000Z",
          "scheduledLabel": "2026-06-08 21:00 +0300",
          "owner": "Dexter",
          "channel": "X / short feed",
          "mode": "manual post",
          "action": "Post final-day football challenge hook",
          "asset": "media/worldcup26-referral-16x9.jpg",
          "trackedLink": "https://worldcup26.world/login?ref=26BC4B90CB&utm_source=x-short-feed&utm_medium=manual-post&utm_campaign=worldcup26_referral_72h&utm_content=dexter_h65",
          "status": "queued"
        }
      ]
    },
    {
      "owner": "Sienna",
      "lane": "Visual captions, stories, reels, and community posts",
      "overdueCount": 19,
      "dueNowCount": 0,
      "dueCount": 19,
      "upcomingCount": 3,
      "readyCount": 8,
      "next": {
        "scheduledAt": "2026-06-06T01:00:00.000Z",
        "scheduledLabel": "2026-06-06 04:00 +0300",
        "owner": "Sienna",
        "channel": "WhatsApp Status",
        "mode": "manual post",
        "action": "Post story asset with video caption 1",
        "asset": "media/worldcup26-main-video.mp4",
        "trackedLink": "https://worldcup26.world/login?ref=26BC4B90CB&utm_source=whatsapp-status&utm_medium=manual-post&utm_campaign=worldcup26_referral_72h&utm_content=sienna_h0",
        "status": "queued"
      },
      "overdue": [
        {
          "scheduledAt": "2026-06-06T01:00:00.000Z",
          "scheduledLabel": "2026-06-06 04:00 +0300",
          "owner": "Sienna",
          "channel": "WhatsApp Status",
          "mode": "manual post",
          "action": "Post story asset with video caption 1",
          "asset": "media/worldcup26-main-video.mp4",
          "trackedLink": "https://worldcup26.world/login?ref=26BC4B90CB&utm_source=whatsapp-status&utm_medium=manual-post&utm_campaign=worldcup26_referral_72h&utm_content=sienna_h0",
          "status": "queued"
        },
        {
          "scheduledAt": "2026-06-06T04:00:00.000Z",
          "scheduledLabel": "2026-06-06 07:00 +0300",
          "owner": "Sienna",
          "channel": "Instagram/Facebook story",
          "mode": "manual post",
          "action": "Story: Code 26BC4B90CB + link sticker",
          "asset": "media/worldcup26-referral-story.jpg",
          "trackedLink": "https://worldcup26.world/login?ref=26BC4B90CB&utm_source=instagram-facebook-story&utm_medium=manual-post&utm_campaign=worldcup26_referral_72h&utm_content=sienna_h3",
          "status": "queued"
        },
        {
          "scheduledAt": "2026-06-06T06:00:00.000Z",
          "scheduledLabel": "2026-06-06 09:00 +0300",
          "owner": "Sienna",
          "channel": "TikTok/Reels/Shorts",
          "mode": "manual post",
          "action": "Upload main video with short caption and code in first line",
          "asset": "media/worldcup26-main-video.mp4",
          "trackedLink": "https://worldcup26.world/login?ref=26BC4B90CB&utm_source=tiktok-reels-shorts&utm_medium=manual-post&utm_campaign=worldcup26_referral_72h&utm_content=sienna_h5",
          "status": "queued"
        },
        {
          "scheduledAt": "2026-06-06T09:00:00.000Z",
          "scheduledLabel": "2026-06-06 12:00 +0300",
          "owner": "Sienna",
          "channel": "YouTube Shorts",
          "mode": "manual post",
          "action": "Post main video as Shorts with code and link in description",
          "asset": "media/worldcup26-main-video.mp4",
          "trackedLink": "https://worldcup26.world/login?ref=26BC4B90CB&utm_source=youtube-shorts&utm_medium=manual-post&utm_campaign=worldcup26_referral_72h&utm_content=sienna_h8",
          "status": "queued"
        },
        {
          "scheduledAt": "2026-06-06T12:00:00.000Z",
          "scheduledLabel": "2026-06-06 15:00 +0300",
          "owner": "Sienna",
          "channel": "Instagram Story",
          "mode": "manual post",
          "action": "Post referral story image with link sticker and code overlay",
          "asset": "media/worldcup26-referral-story.jpg",
          "trackedLink": "https://worldcup26.world/login?ref=26BC4B90CB&utm_source=instagram-story&utm_medium=manual-post&utm_campaign=worldcup26_referral_72h&utm_content=sienna_h11",
          "status": "queued"
        },
        {
          "scheduledAt": "2026-06-06T16:00:00.000Z",
          "scheduledLabel": "2026-06-06 19:00 +0300",
          "owner": "Sienna",
          "channel": "Facebook Reels",
          "mode": "manual post",
          "action": "Upload main video as Reel with code in caption",
          "asset": "media/worldcup26-main-video.mp4",
          "trackedLink": "https://worldcup26.world/login?ref=26BC4B90CB&utm_source=facebook-reels&utm_medium=manual-post&utm_campaign=worldcup26_referral_72h&utm_content=sienna_h15",
          "status": "queued"
        }
      ],
      "dueNow": [],
      "upcoming": [
        {
          "scheduledAt": "2026-06-08T08:00:00.000Z",
          "scheduledLabel": "2026-06-08 11:00 +0300",
          "owner": "Sienna",
          "channel": "YouTube Shorts",
          "mode": "manual post",
          "action": "Post video with code and short description",
          "asset": "media/worldcup26-main-video.mp4",
          "trackedLink": "https://worldcup26.world/login?ref=26BC4B90CB&utm_source=youtube-shorts&utm_medium=manual-post&utm_campaign=worldcup26_referral_72h&utm_content=sienna_h55",
          "status": "queued"
        },
        {
          "scheduledAt": "2026-06-08T12:00:00.000Z",
          "scheduledLabel": "2026-06-08 15:00 +0300",
          "owner": "Sienna",
          "channel": "Facebook Reels",
          "mode": "manual post",
          "action": "Repost main video with friends-angle caption",
          "asset": "media/worldcup26-main-video.mp4",
          "trackedLink": "https://worldcup26.world/login?ref=26BC4B90CB&utm_source=facebook-reels&utm_medium=manual-post&utm_campaign=worldcup26_referral_72h&utm_content=sienna_h59",
          "status": "queued"
        },
        {
          "scheduledAt": "2026-06-08T15:00:00.000Z",
          "scheduledLabel": "2026-06-08 18:00 +0300",
          "owner": "Sienna",
          "channel": "Instagram Story",
          "mode": "manual post",
          "action": "Story: three-pick challenge + link sticker",
          "asset": "media/worldcup26-referral-story.jpg",
          "trackedLink": "https://worldcup26.world/login?ref=26BC4B90CB&utm_source=instagram-story&utm_medium=manual-post&utm_campaign=worldcup26_referral_72h&utm_content=sienna_h62",
          "status": "queued"
        }
      ]
    },
    {
      "owner": "Memo",
      "lane": "Ops tracker and campaign log",
      "overdueCount": 5,
      "dueNowCount": 0,
      "dueCount": 5,
      "upcomingCount": 2,
      "readyCount": 7,
      "next": {
        "scheduledAt": "2026-06-06T21:00:00.000Z",
        "scheduledLabel": "2026-06-07 00:00 +0300",
        "owner": "Memo",
        "channel": "Ops check",
        "mode": "internal",
        "action": "Summarize Day 1: posts, replies, joins observed, next 5 actions",
        "asset": "campaign/posting-log-template.csv",
        "trackedLink": "https://worldcup26.world/login?ref=26BC4B90CB&utm_source=ops-check&utm_medium=internal&utm_campaign=worldcup26_referral_72h&utm_content=memo_h20",
        "status": "queued"
      },
      "overdue": [
        {
          "scheduledAt": "2026-06-06T21:00:00.000Z",
          "scheduledLabel": "2026-06-07 00:00 +0300",
          "owner": "Memo",
          "channel": "Ops check",
          "mode": "internal",
          "action": "Summarize Day 1: posts, replies, joins observed, next 5 actions",
          "asset": "campaign/posting-log-template.csv",
          "trackedLink": "https://worldcup26.world/login?ref=26BC4B90CB&utm_source=ops-check&utm_medium=internal&utm_campaign=worldcup26_referral_72h&utm_content=memo_h20",
          "status": "queued"
        },
        {
          "scheduledAt": "2026-06-07T06:00:00.000Z",
          "scheduledLabel": "2026-06-07 09:00 +0300",
          "owner": "Memo",
          "channel": "Ops check",
          "mode": "internal",
          "action": "Audit completed posts and add missing links to log",
          "asset": "campaign/posting-log-template.csv",
          "trackedLink": "https://worldcup26.world/login?ref=26BC4B90CB&utm_source=ops-check&utm_medium=internal&utm_campaign=worldcup26_referral_72h&utm_content=memo_h29",
          "status": "queued"
        },
        {
          "scheduledAt": "2026-06-07T13:00:00.000Z",
          "scheduledLabel": "2026-06-07 16:00 +0300",
          "owner": "Memo",
          "channel": "Ops check",
          "mode": "internal",
          "action": "Update channel performance and pending replies",
          "asset": "campaign/posting-log-template.csv",
          "trackedLink": "https://worldcup26.world/login?ref=26BC4B90CB&utm_source=ops-check&utm_medium=internal&utm_campaign=worldcup26_referral_72h&utm_content=memo_h36",
          "status": "queued"
        },
        {
          "scheduledAt": "2026-06-07T20:00:00.000Z",
          "scheduledLabel": "2026-06-07 23:00 +0300",
          "owner": "Memo",
          "channel": "Ops check",
          "mode": "internal",
          "action": "List channels with permission granted and blocked channels to avoid",
          "asset": "campaign/partner-targets-template.csv",
          "trackedLink": "https://worldcup26.world/login?ref=26BC4B90CB&utm_source=ops-check&utm_medium=internal&utm_campaign=worldcup26_referral_72h&utm_content=memo_h43",
          "status": "queued"
        },
        {
          "scheduledAt": "2026-06-08T04:00:00.000Z",
          "scheduledLabel": "2026-06-08 07:00 +0300",
          "owner": "Memo",
          "channel": "Ops check",
          "mode": "internal",
          "action": "Check if any copy claims a fixed prize; remove fixed amount before posting",
          "asset": "campaign/copy-bank.md",
          "trackedLink": "https://worldcup26.world/login?ref=26BC4B90CB&utm_source=ops-check&utm_medium=internal&utm_campaign=worldcup26_referral_72h&utm_content=memo_h51",
          "status": "queued"
        }
      ],
      "dueNow": [],
      "upcoming": [
        {
          "scheduledAt": "2026-06-08T09:00:00.000Z",
          "scheduledLabel": "2026-06-08 12:00 +0300",
          "owner": "Memo",
          "channel": "Ops check",
          "mode": "internal",
          "action": "Choose best two channels and double posting cadence there",
          "asset": "campaign/posting-log-template.csv",
          "trackedLink": "https://worldcup26.world/login?ref=26BC4B90CB&utm_source=ops-check&utm_medium=internal&utm_campaign=worldcup26_referral_72h&utm_content=memo_h56",
          "status": "queued"
        },
        {
          "scheduledAt": "2026-06-08T16:00:00.000Z",
          "scheduledLabel": "2026-06-08 19:00 +0300",
          "owner": "Memo",
          "channel": "Ops check",
          "mode": "internal",
          "action": "Prepare final-day push list from best channels and replies",
          "asset": "campaign/posting-log-template.csv",
          "trackedLink": "https://worldcup26.world/login?ref=26BC4B90CB&utm_source=ops-check&utm_medium=internal&utm_campaign=worldcup26_referral_72h&utm_content=memo_h63",
          "status": "queued"
        }
      ]
    },
    {
      "owner": "Nano",
      "lane": "Replies, DMs, objections, and micro-posts",
      "overdueCount": 13,
      "dueNowCount": 0,
      "dueCount": 13,
      "upcomingCount": 4,
      "readyCount": 8,
      "next": {
        "scheduledAt": "2026-06-06T03:00:00.000Z",
        "scheduledLabel": "2026-06-06 06:00 +0300",
        "owner": "Nano",
        "channel": "WhatsApp personal",
        "mode": "manual outreach",
        "action": "Send personal invite to warm contacts",
        "asset": "media/worldcup26-main-video.mp4",
        "trackedLink": "https://worldcup26.world/login?ref=26BC4B90CB&utm_source=whatsapp-personal&utm_medium=manual-outreach&utm_campaign=worldcup26_referral_72h&utm_content=nano_h2",
        "status": "queued"
      },
      "overdue": [
        {
          "scheduledAt": "2026-06-06T03:00:00.000Z",
          "scheduledLabel": "2026-06-06 06:00 +0300",
          "owner": "Nano",
          "channel": "WhatsApp personal",
          "mode": "manual outreach",
          "action": "Send personal invite to warm contacts",
          "asset": "media/worldcup26-main-video.mp4",
          "trackedLink": "https://worldcup26.world/login?ref=26BC4B90CB&utm_source=whatsapp-personal&utm_medium=manual-outreach&utm_campaign=worldcup26_referral_72h&utm_content=nano_h2",
          "status": "queued"
        },
        {
          "scheduledAt": "2026-06-06T08:00:00.000Z",
          "scheduledLabel": "2026-06-06 11:00 +0300",
          "owner": "Nano",
          "channel": "DM follow-up",
          "mode": "manual replies",
          "action": "Reply to first reactions and send the simple how-it-works answer",
          "asset": "campaign/copy-bank.md",
          "trackedLink": "https://worldcup26.world/login?ref=26BC4B90CB&utm_source=dm-follow-up&utm_medium=manual-replies&utm_campaign=worldcup26_referral_72h&utm_content=nano_h7",
          "status": "queued"
        },
        {
          "scheduledAt": "2026-06-06T11:00:00.000Z",
          "scheduledLabel": "2026-06-06 14:00 +0300",
          "owner": "Nano",
          "channel": "Replies",
          "mode": "manual replies",
          "action": "Answer questions using reply bank; push code/link once per conversation",
          "asset": "campaign/copy-bank.md",
          "trackedLink": "https://worldcup26.world/login?ref=26BC4B90CB&utm_source=replies&utm_medium=manual-replies&utm_campaign=worldcup26_referral_72h&utm_content=nano_h10",
          "status": "queued"
        },
        {
          "scheduledAt": "2026-06-06T14:00:00.000Z",
          "scheduledLabel": "2026-06-06 17:00 +0300",
          "owner": "Nano",
          "channel": "WhatsApp personal",
          "mode": "manual outreach",
          "action": "Send second warm-contact batch with main invite",
          "asset": "media/worldcup26-main-video.mp4",
          "trackedLink": "https://worldcup26.world/login?ref=26BC4B90CB&utm_source=whatsapp-personal&utm_medium=manual-outreach&utm_campaign=worldcup26_referral_72h&utm_content=nano_h13",
          "status": "queued"
        },
        {
          "scheduledAt": "2026-06-06T19:00:00.000Z",
          "scheduledLabel": "2026-06-06 22:00 +0300",
          "owner": "Nano",
          "channel": "Direct DMs",
          "mode": "manual outreach",
          "action": "Send one-to-one invite to people who reacted to stories",
          "asset": "campaign/copy-bank.md",
          "trackedLink": "https://worldcup26.world/login?ref=26BC4B90CB&utm_source=direct-dms&utm_medium=manual-outreach&utm_campaign=worldcup26_referral_72h&utm_content=nano_h18",
          "status": "queued"
        },
        {
          "scheduledAt": "2026-06-06T23:00:00.000Z",
          "scheduledLabel": "2026-06-07 02:00 +0300",
          "owner": "Nano",
          "channel": "Community replies",
          "mode": "manual replies",
          "action": "Answer how many teams and why code matters",
          "asset": "campaign/copy-bank.md",
          "trackedLink": "https://worldcup26.world/login?ref=26BC4B90CB&utm_source=community-replies&utm_medium=manual-replies&utm_campaign=worldcup26_referral_72h&utm_content=nano_h22",
          "status": "queued"
        }
      ],
      "dueNow": [],
      "upcoming": [
        {
          "scheduledAt": "2026-06-08T07:00:00.000Z",
          "scheduledLabel": "2026-06-08 10:00 +0300",
          "owner": "Nano",
          "channel": "WhatsApp personal",
          "mode": "manual outreach",
          "action": "Invite warm-contact batch with simple personal message",
          "asset": "media/worldcup26-main-video.mp4",
          "trackedLink": "https://worldcup26.world/login?ref=26BC4B90CB&utm_source=whatsapp-personal&utm_medium=manual-outreach&utm_campaign=worldcup26_referral_72h&utm_content=nano_h54",
          "status": "queued"
        },
        {
          "scheduledAt": "2026-06-08T11:00:00.000Z",
          "scheduledLabel": "2026-06-08 14:00 +0300",
          "owner": "Nano",
          "channel": "Replies",
          "mode": "manual replies",
          "action": "Answer late replies and resend link once if requested",
          "asset": "campaign/copy-bank.md",
          "trackedLink": "https://worldcup26.world/login?ref=26BC4B90CB&utm_source=replies&utm_medium=manual-replies&utm_campaign=worldcup26_referral_72h&utm_content=nano_h58",
          "status": "queued"
        },
        {
          "scheduledAt": "2026-06-08T14:00:00.000Z",
          "scheduledLabel": "2026-06-08 17:00 +0300",
          "owner": "Nano",
          "channel": "Direct DMs",
          "mode": "manual outreach",
          "action": "Ask interested contacts if they want the invite link again",
          "asset": "campaign/copy-bank.md",
          "trackedLink": "https://worldcup26.world/login?ref=26BC4B90CB&utm_source=direct-dms&utm_medium=manual-outreach&utm_campaign=worldcup26_referral_72h&utm_content=nano_h61",
          "status": "queued"
        },
        {
          "scheduledAt": "2026-06-08T17:00:00.000Z",
          "scheduledLabel": "2026-06-08 20:00 +0300",
          "owner": "Nano",
          "channel": "Warm contacts",
          "mode": "manual outreach",
          "action": "Ask joined users to invite 3 friends",
          "asset": "campaign/copy-bank.md",
          "trackedLink": "https://worldcup26.world/login?ref=26BC4B90CB&utm_source=warm-contacts&utm_medium=manual-outreach&utm_campaign=worldcup26_referral_72h&utm_content=nano_h64",
          "status": "queued"
        }
      ]
    }
  ],
  "nextActions": [
    {
      "scheduledAt": "2026-06-06T01:00:00.000Z",
      "scheduledLabel": "2026-06-06 04:00 +0300",
      "owner": "Sienna",
      "channel": "WhatsApp Status",
      "mode": "manual post",
      "action": "Post story asset with video caption 1",
      "asset": "media/worldcup26-main-video.mp4",
      "trackedLink": "https://worldcup26.world/login?ref=26BC4B90CB&utm_source=whatsapp-status&utm_medium=manual-post&utm_campaign=worldcup26_referral_72h&utm_content=sienna_h0",
      "status": "queued"
    },
    {
      "scheduledAt": "2026-06-06T03:00:00.000Z",
      "scheduledLabel": "2026-06-06 06:00 +0300",
      "owner": "Nano",
      "channel": "WhatsApp personal",
      "mode": "manual outreach",
      "action": "Send personal invite to warm contacts",
      "asset": "media/worldcup26-main-video.mp4",
      "trackedLink": "https://worldcup26.world/login?ref=26BC4B90CB&utm_source=whatsapp-personal&utm_medium=manual-outreach&utm_campaign=worldcup26_referral_72h&utm_content=nano_h2",
      "status": "queued"
    },
    {
      "scheduledAt": "2026-06-06T05:00:00.000Z",
      "scheduledLabel": "2026-06-06 08:00 +0300",
      "owner": "Dexter",
      "channel": "Football groups",
      "mode": "approval first",
      "action": "Ask approved group admin for permission; post group variant only if allowed",
      "asset": "campaign/first-wave-posts.md",
      "trackedLink": "https://worldcup26.world/login?ref=26BC4B90CB&utm_source=football-groups&utm_medium=approval-first&utm_campaign=worldcup26_referral_72h&utm_content=dexter_h4",
      "status": "queued"
    },
    {
      "scheduledAt": "2026-06-06T21:00:00.000Z",
      "scheduledLabel": "2026-06-07 00:00 +0300",
      "owner": "Memo",
      "channel": "Ops check",
      "mode": "internal",
      "action": "Summarize Day 1: posts, replies, joins observed, next 5 actions",
      "asset": "campaign/posting-log-template.csv",
      "trackedLink": "https://worldcup26.world/login?ref=26BC4B90CB&utm_source=ops-check&utm_medium=internal&utm_campaign=worldcup26_referral_72h&utm_content=memo_h20",
      "status": "queued"
    }
  ],
  "urgentActions": [
    {
      "scheduledAt": "2026-06-06T01:00:00.000Z",
      "scheduledLabel": "2026-06-06 04:00 +0300",
      "owner": "Sienna",
      "channel": "WhatsApp Status",
      "mode": "manual post",
      "action": "Post story asset with video caption 1",
      "asset": "media/worldcup26-main-video.mp4",
      "trackedLink": "https://worldcup26.world/login?ref=26BC4B90CB&utm_source=whatsapp-status&utm_medium=manual-post&utm_campaign=worldcup26_referral_72h&utm_content=sienna_h0",
      "status": "queued"
    },
    {
      "scheduledAt": "2026-06-06T03:00:00.000Z",
      "scheduledLabel": "2026-06-06 06:00 +0300",
      "owner": "Nano",
      "channel": "WhatsApp personal",
      "mode": "manual outreach",
      "action": "Send personal invite to warm contacts",
      "asset": "media/worldcup26-main-video.mp4",
      "trackedLink": "https://worldcup26.world/login?ref=26BC4B90CB&utm_source=whatsapp-personal&utm_medium=manual-outreach&utm_campaign=worldcup26_referral_72h&utm_content=nano_h2",
      "status": "queued"
    },
    {
      "scheduledAt": "2026-06-06T04:00:00.000Z",
      "scheduledLabel": "2026-06-06 07:00 +0300",
      "owner": "Sienna",
      "channel": "Instagram/Facebook story",
      "mode": "manual post",
      "action": "Story: Code 26BC4B90CB + link sticker",
      "asset": "media/worldcup26-referral-story.jpg",
      "trackedLink": "https://worldcup26.world/login?ref=26BC4B90CB&utm_source=instagram-facebook-story&utm_medium=manual-post&utm_campaign=worldcup26_referral_72h&utm_content=sienna_h3",
      "status": "queued"
    },
    {
      "scheduledAt": "2026-06-06T05:00:00.000Z",
      "scheduledLabel": "2026-06-06 08:00 +0300",
      "owner": "Dexter",
      "channel": "Football groups",
      "mode": "approval first",
      "action": "Ask approved group admin for permission; post group variant only if allowed",
      "asset": "campaign/first-wave-posts.md",
      "trackedLink": "https://worldcup26.world/login?ref=26BC4B90CB&utm_source=football-groups&utm_medium=approval-first&utm_campaign=worldcup26_referral_72h&utm_content=dexter_h4",
      "status": "queued"
    },
    {
      "scheduledAt": "2026-06-06T06:00:00.000Z",
      "scheduledLabel": "2026-06-06 09:00 +0300",
      "owner": "Sienna",
      "channel": "TikTok/Reels/Shorts",
      "mode": "manual post",
      "action": "Upload main video with short caption and code in first line",
      "asset": "media/worldcup26-main-video.mp4",
      "trackedLink": "https://worldcup26.world/login?ref=26BC4B90CB&utm_source=tiktok-reels-shorts&utm_medium=manual-post&utm_campaign=worldcup26_referral_72h&utm_content=sienna_h5",
      "status": "queued"
    },
    {
      "scheduledAt": "2026-06-06T08:00:00.000Z",
      "scheduledLabel": "2026-06-06 11:00 +0300",
      "owner": "Nano",
      "channel": "DM follow-up",
      "mode": "manual replies",
      "action": "Reply to first reactions and send the simple how-it-works answer",
      "asset": "campaign/copy-bank.md",
      "trackedLink": "https://worldcup26.world/login?ref=26BC4B90CB&utm_source=dm-follow-up&utm_medium=manual-replies&utm_campaign=worldcup26_referral_72h&utm_content=nano_h7",
      "status": "queued"
    },
    {
      "scheduledAt": "2026-06-06T09:00:00.000Z",
      "scheduledLabel": "2026-06-06 12:00 +0300",
      "owner": "Sienna",
      "channel": "YouTube Shorts",
      "mode": "manual post",
      "action": "Post main video as Shorts with code and link in description",
      "asset": "media/worldcup26-main-video.mp4",
      "trackedLink": "https://worldcup26.world/login?ref=26BC4B90CB&utm_source=youtube-shorts&utm_medium=manual-post&utm_campaign=worldcup26_referral_72h&utm_content=sienna_h8",
      "status": "queued"
    },
    {
      "scheduledAt": "2026-06-06T10:00:00.000Z",
      "scheduledLabel": "2026-06-06 13:00 +0300",
      "owner": "Dexter",
      "channel": "Facebook profile/page",
      "mode": "manual post",
      "action": "Publish simple rules feed post for friends and football contacts",
      "asset": "media/worldcup26-referral-square.jpg",
      "trackedLink": "https://worldcup26.world/login?ref=26BC4B90CB&utm_source=facebook-profile-page&utm_medium=manual-post&utm_campaign=worldcup26_referral_72h&utm_content=dexter_h9",
      "status": "queued"
    },
    {
      "scheduledAt": "2026-06-06T11:00:00.000Z",
      "scheduledLabel": "2026-06-06 14:00 +0300",
      "owner": "Nano",
      "channel": "Replies",
      "mode": "manual replies",
      "action": "Answer questions using reply bank; push code/link once per conversation",
      "asset": "campaign/copy-bank.md",
      "trackedLink": "https://worldcup26.world/login?ref=26BC4B90CB&utm_source=replies&utm_medium=manual-replies&utm_campaign=worldcup26_referral_72h&utm_content=nano_h10",
      "status": "queued"
    },
    {
      "scheduledAt": "2026-06-06T12:00:00.000Z",
      "scheduledLabel": "2026-06-06 15:00 +0300",
      "owner": "Sienna",
      "channel": "Instagram Story",
      "mode": "manual post",
      "action": "Post referral story image with link sticker and code overlay",
      "asset": "media/worldcup26-referral-story.jpg",
      "trackedLink": "https://worldcup26.world/login?ref=26BC4B90CB&utm_source=instagram-story&utm_medium=manual-post&utm_campaign=worldcup26_referral_72h&utm_content=sienna_h11",
      "status": "queued"
    },
    {
      "scheduledAt": "2026-06-06T14:00:00.000Z",
      "scheduledLabel": "2026-06-06 17:00 +0300",
      "owner": "Nano",
      "channel": "WhatsApp personal",
      "mode": "manual outreach",
      "action": "Send second warm-contact batch with main invite",
      "asset": "media/worldcup26-main-video.mp4",
      "trackedLink": "https://worldcup26.world/login?ref=26BC4B90CB&utm_source=whatsapp-personal&utm_medium=manual-outreach&utm_campaign=worldcup26_referral_72h&utm_content=nano_h13",
      "status": "queued"
    },
    {
      "scheduledAt": "2026-06-06T16:00:00.000Z",
      "scheduledLabel": "2026-06-06 19:00 +0300",
      "owner": "Sienna",
      "channel": "Facebook Reels",
      "mode": "manual post",
      "action": "Upload main video as Reel with code in caption",
      "asset": "media/worldcup26-main-video.mp4",
      "trackedLink": "https://worldcup26.world/login?ref=26BC4B90CB&utm_source=facebook-reels&utm_medium=manual-post&utm_campaign=worldcup26_referral_72h&utm_content=sienna_h15",
      "status": "queued"
    },
    {
      "scheduledAt": "2026-06-06T17:00:00.000Z",
      "scheduledLabel": "2026-06-06 20:00 +0300",
      "owner": "Sienna",
      "channel": "WhatsApp/Telegram groups",
      "mode": "approval first",
      "action": "Community post variant if promo welcome",
      "asset": "media/worldcup26-referral-story.jpg",
      "trackedLink": "https://worldcup26.world/login?ref=26BC4B90CB&utm_source=whatsapp-telegram-groups&utm_medium=approval-first&utm_campaign=worldcup26_referral_72h&utm_content=sienna_h16",
      "status": "queued"
    },
    {
      "scheduledAt": "2026-06-06T18:00:00.000Z",
      "scheduledLabel": "2026-06-06 21:00 +0300",
      "owner": "Dexter",
      "channel": "Creator outreach",
      "mode": "manual outreach",
      "action": "Send partner DM to football micro-creators",
      "asset": "campaign/first-wave-posts.md",
      "trackedLink": "https://worldcup26.world/login?ref=26BC4B90CB&utm_source=creator-outreach&utm_medium=manual-outreach&utm_campaign=worldcup26_referral_72h&utm_content=dexter_h17",
      "status": "queued"
    },
    {
      "scheduledAt": "2026-06-06T19:00:00.000Z",
      "scheduledLabel": "2026-06-06 22:00 +0300",
      "owner": "Nano",
      "channel": "Direct DMs",
      "mode": "manual outreach",
      "action": "Send one-to-one invite to people who reacted to stories",
      "asset": "campaign/copy-bank.md",
      "trackedLink": "https://worldcup26.world/login?ref=26BC4B90CB&utm_source=direct-dms&utm_medium=manual-outreach&utm_campaign=worldcup26_referral_72h&utm_content=nano_h18",
      "status": "queued"
    },
    {
      "scheduledAt": "2026-06-06T20:00:00.000Z",
      "scheduledLabel": "2026-06-06 23:00 +0300",
      "owner": "Sienna",
      "channel": "TikTok/Reels/Shorts",
      "mode": "manual post",
      "action": "Repost video with favorites-or-underdogs caption",
      "asset": "media/worldcup26-main-video.mp4",
      "trackedLink": "https://worldcup26.world/login?ref=26BC4B90CB&utm_source=tiktok-reels-shorts&utm_medium=manual-post&utm_campaign=worldcup26_referral_72h&utm_content=sienna_h19",
      "status": "queued"
    }
  ]
}
